{
  "backend_dir": "/home/runner/work/parser_en/parser_en/backend",
  "total": 12,
  "success": 12,
  "failures": 0,
  "results": [
    {
      "script": "atlantic.py",
      "returncode": 0,
      "started_at": "2025-09-08T09:26:31.506758Z",
      "ended_at": "2025-09-08T09:26:32.436461Z",
      "stdout": "",
      "stderr": ""
    },
    {
      "script": "gq.py",
      "returncode": 0,
      "started_at": "2025-09-08T09:26:32.436482Z",
      "ended_at": "2025-09-08T09:26:34.676928Z",
      "stdout": "",
      "stderr": ""
    },
    {
      "script": "newyorker.py",
      "returncode": 0,
      "started_at": "2025-09-08T09:26:34.676949Z",
      "ended_at": "2025-09-08T09:26:35.687016Z",
      "stdout": "",
      "stderr": ""
    },
    {
      "script": "nyt.py",
      "returncode": 0,
      "started_at": "2025-09-08T09:26:35.687038Z",
      "ended_at": "2025-09-08T09:26:36.145300Z",
      "stdout": "",
      "stderr": ""
    },
    {
      "script": "nytmag.py",
      "returncode": 0,
      "started_at": "2025-09-08T09:26:36.145321Z",
      "ended_at": "2025-09-08T09:26:36.442046Z",
      "stdout": "",
      "stderr": ""
    },
    {
      "script": "reuters.py",
      "returncode": 0,
      "started_at": "2025-09-08T09:26:36.442067Z",
      "ended_at": "2025-09-08T09:27:01.423232Z",
      "stdout": "Collected 0 items\n",
      "stderr": ""
    },
    {
      "script": "semafor.py",
      "returncode": 0,
      "started_at": "2025-09-08T09:27:01.423253Z",
      "ended_at": "2025-09-08T09:27:01.790731Z",
      "stdout": "",
      "stderr": ""
    },
    {
      "script": "vulture.py",
      "returncode": 0,
      "started_at": "2025-09-08T09:27:01.790754Z",
      "ended_at": "2025-09-08T09:27:02.573021Z",
      "stdout": "",
      "stderr": ""
    },
    {
      "script": "wired.py",
      "returncode": 0,
      "started_at": "2025-09-08T09:27:02.573041Z",
      "ended_at": "2025-09-08T09:27:06.754967Z",
      "stdout": "",
      "stderr": ""
    },
    {
      "script": "wp_internet.py",
      "returncode": 0,
      "started_at": "2025-09-08T09:27:06.754993Z",
      "ended_at": "2025-09-08T09:27:11.370922Z",
      "stdout": "✅ RSS создан: /home/runner/work/parser_en/parser_en/wapo_internet.xml, статей собрано: 0\n",
      "stderr": ""
    },
    {
      "script": "wp_inv.py",
      "returncode": 0,
      "started_at": "2025-09-08T09:27:11.370944Z",
      "ended_at": "2025-09-08T09:27:14.950677Z",
      "stdout": "RSS создан: /home/runner/work/parser_en/parser_en/wapo_inv.xml\n",
      "stderr": ""
    },
    {
      "script": "wp_tech.py",
      "returncode": 0,
      "started_at": "2025-09-08T09:27:14.950702Z",
      "ended_at": "2025-09-08T09:27:18.630184Z",
      "stdout": "Добавлена статья: Tech in Your Life\nДобавлена статья: Your Data and Privacy\nДобавлена статья: Internet Access\nДобавлена статья: What's New\nДобавлена статья: Ethical Issues\n✅ RSS создан: /home/runner/work/parser_en/parser_en/wapo_tech.xml, статей собрано: 5\n",
      "stderr": ""
    }
  ]
}