{
  "backend_dir": "/home/runner/work/parser_en/parser_en/backend",
  "total": 15,
  "success": 15,
  "failures": 0,
  "results": [
    {
      "script": "atlantic.py",
      "returncode": 0,
      "started_at": "2026-04-24T18:34:32.599840Z",
      "ended_at": "2026-04-24T18:34:34.052585Z",
      "stdout": "",
      "stderr": ""
    },
    {
      "script": "gallup.py",
      "returncode": 0,
      "started_at": "2026-04-24T18:34:34.052609Z",
      "ended_at": "2026-04-24T18:34:34.101446Z",
      "stdout": "⚠️  Skipping parsing: gallup.py (site temporarily unavailable)\n✅ Stub RSS written: /home/runner/work/parser_en/parser_en/backend/../gallup.xml\n",
      "stderr": ""
    },
    {
      "script": "gq.py",
      "returncode": 0,
      "started_at": "2026-04-24T18:34:34.101464Z",
      "ended_at": "2026-04-24T18:34:34.752805Z",
      "stdout": "",
      "stderr": ""
    },
    {
      "script": "macleans1.py",
      "returncode": 0,
      "started_at": "2026-04-24T18:34:34.752831Z",
      "ended_at": "2026-04-24T18:34:34.801677Z",
      "stdout": "⚠️  Skipping parsing: macleans1.py (site temporarily unavailable)\n✅ Stub RSS written: /home/runner/work/parser_en/parser_en/backend/../macleans1.xml\n",
      "stderr": ""
    },
    {
      "script": "newyorker.py",
      "returncode": 0,
      "started_at": "2026-04-24T18:34:34.801698Z",
      "ended_at": "2026-04-24T18:34:36.365608Z",
      "stdout": "",
      "stderr": ""
    },
    {
      "script": "nyt.py",
      "returncode": 0,
      "started_at": "2026-04-24T18:34:36.365632Z",
      "ended_at": "2026-04-24T18:34:36.844115Z",
      "stdout": "",
      "stderr": ""
    },
    {
      "script": "nytmag.py",
      "returncode": 0,
      "started_at": "2026-04-24T18:34:36.844141Z",
      "ended_at": "2026-04-24T18:34:37.223270Z",
      "stdout": "",
      "stderr": ""
    },
    {
      "script": "pitchfork.py",
      "returncode": 0,
      "started_at": "2026-04-24T18:34:37.223295Z",
      "ended_at": "2026-04-24T18:34:37.850789Z",
      "stdout": "📰 Found 0 articles. Fetching dates...\n✅ pitchfork.xml generated successfully\n",
      "stderr": ""
    },
    {
      "script": "reuters.py",
      "returncode": 0,
      "started_at": "2026-04-24T18:34:37.850813Z",
      "ended_at": "2026-04-24T18:35:02.797290Z",
      "stdout": "Collected 0 items\n",
      "stderr": ""
    },
    {
      "script": "semafor.py",
      "returncode": 0,
      "started_at": "2026-04-24T18:35:02.797312Z",
      "ended_at": "2026-04-24T18:35:03.256147Z",
      "stdout": "",
      "stderr": ""
    },
    {
      "script": "vulture.py",
      "returncode": 0,
      "started_at": "2026-04-24T18:35:03.256169Z",
      "ended_at": "2026-04-24T18:35:03.549343Z",
      "stdout": "",
      "stderr": ""
    },
    {
      "script": "wired.py",
      "returncode": 0,
      "started_at": "2026-04-24T18:35:03.549365Z",
      "ended_at": "2026-04-24T18:35:04.003597Z",
      "stdout": "",
      "stderr": ""
    },
    {
      "script": "wp_internet.py",
      "returncode": 0,
      "started_at": "2026-04-24T18:35:04.003621Z",
      "ended_at": "2026-04-24T18:35:08.074202Z",
      "stdout": "✅ RSS создан: /home/runner/work/parser_en/parser_en/wapo_internet.xml, статей собрано: 0\n",
      "stderr": ""
    },
    {
      "script": "wp_inv.py",
      "returncode": 0,
      "started_at": "2026-04-24T18:35:08.074223Z",
      "ended_at": "2026-04-24T18:35:12.054830Z",
      "stdout": "RSS создан: /home/runner/work/parser_en/parser_en/wapo_inv.xml\n",
      "stderr": ""
    },
    {
      "script": "wp_tech.py",
      "returncode": 0,
      "started_at": "2026-04-24T18:35:12.054851Z",
      "ended_at": "2026-04-24T18:35:16.929129Z",
      "stdout": "Добавлена статья: Tech in Your Life\nДобавлена статья: Your Data and Privacy\nДобавлена статья: Internet Access\nДобавлена статья: What's New\nДобавлена статья: Ethical Issues\n✅ RSS создан: /home/runner/work/parser_en/parser_en/wapo_tech.xml, статей собрано: 5\n",
      "stderr": ""
    }
  ]
}