{
  "backend_dir": "/home/runner/work/parser_en/parser_en/backend",
  "total": 12,
  "success": 12,
  "failures": 0,
  "results": [
    {
      "script": "atlantic.py",
      "returncode": 0,
      "started_at": "2025-11-07T20:23:21.986582Z",
      "ended_at": "2025-11-07T20:23:22.794218Z",
      "stdout": "",
      "stderr": ""
    },
    {
      "script": "gq.py",
      "returncode": 0,
      "started_at": "2025-11-07T20:23:22.794251Z",
      "ended_at": "2025-11-07T20:23:24.973405Z",
      "stdout": "",
      "stderr": ""
    },
    {
      "script": "newyorker.py",
      "returncode": 0,
      "started_at": "2025-11-07T20:23:24.973428Z",
      "ended_at": "2025-11-07T20:23:25.540951Z",
      "stdout": "",
      "stderr": ""
    },
    {
      "script": "nyt.py",
      "returncode": 0,
      "started_at": "2025-11-07T20:23:25.540974Z",
      "ended_at": "2025-11-07T20:23:26.191684Z",
      "stdout": "",
      "stderr": ""
    },
    {
      "script": "nytmag.py",
      "returncode": 0,
      "started_at": "2025-11-07T20:23:26.191709Z",
      "ended_at": "2025-11-07T20:23:26.534139Z",
      "stdout": "",
      "stderr": ""
    },
    {
      "script": "reuters.py",
      "returncode": 0,
      "started_at": "2025-11-07T20:23:26.534161Z",
      "ended_at": "2025-11-07T20:23:51.653981Z",
      "stdout": "Collected 0 items\n",
      "stderr": ""
    },
    {
      "script": "semafor.py",
      "returncode": 0,
      "started_at": "2025-11-07T20:23:51.654004Z",
      "ended_at": "2025-11-07T20:23:52.147102Z",
      "stdout": "",
      "stderr": ""
    },
    {
      "script": "vulture.py",
      "returncode": 0,
      "started_at": "2025-11-07T20:23:52.147126Z",
      "ended_at": "2025-11-07T20:23:52.444944Z",
      "stdout": "",
      "stderr": ""
    },
    {
      "script": "wired.py",
      "returncode": 0,
      "started_at": "2025-11-07T20:23:52.444970Z",
      "ended_at": "2025-11-07T20:24:10.687472Z",
      "stdout": "[WARN] Не удалось получить дату для https://www.wired.com/visual-story/ai-issue/\n[WARN] Не удалось получить дату для https://www.wired.com/visual-story/ai-issue-therapist/\n[WARN] Не удалось получить дату для https://www.wired.com/visual-story/ai-issue-teacher/\n[WARN] Не удалось получить дату для https://www.wired.com/visual-story/ai-issue-pr/\n[WARN] Не удалось получить дату для https://www.wired.com/visual-story/ai-issue-black-box/\n[WARN] Не удалось получить дату для https://www.wired.com/visual-story/ai-issue-artist/\n[WARN] Не удалось получить дату для https://www.wired.com/visual-story/ai-issue-bubble/\n[WARN] Не удалось получить дату для https://www.wired.com/ai-issue/\n",
      "stderr": ""
    },
    {
      "script": "wp_internet.py",
      "returncode": 0,
      "started_at": "2025-11-07T20:24:10.687495Z",
      "ended_at": "2025-11-07T20:24:15.155360Z",
      "stdout": "✅ RSS создан: /home/runner/work/parser_en/parser_en/wapo_internet.xml, статей собрано: 0\n",
      "stderr": ""
    },
    {
      "script": "wp_inv.py",
      "returncode": 0,
      "started_at": "2025-11-07T20:24:15.155383Z",
      "ended_at": "2025-11-07T20:24:18.871204Z",
      "stdout": "RSS создан: /home/runner/work/parser_en/parser_en/wapo_inv.xml\n",
      "stderr": ""
    },
    {
      "script": "wp_tech.py",
      "returncode": 0,
      "started_at": "2025-11-07T20:24:18.871230Z",
      "ended_at": "2025-11-07T20:24:22.887822Z",
      "stdout": "Добавлена статья: Tech in Your Life\nДобавлена статья: Your Data and Privacy\nДобавлена статья: Internet Access\nДобавлена статья: What's New\nДобавлена статья: Ethical Issues\n✅ RSS создан: /home/runner/work/parser_en/parser_en/wapo_tech.xml, статей собрано: 5\n",
      "stderr": ""
    }
  ]
}