{
  "backend_dir": "/home/runner/work/parser_en/parser_en/backend",
  "total": 15,
  "success": 15,
  "failures": 0,
  "results": [
    {
      "script": "atlantic.py",
      "returncode": 0,
      "started_at": "2026-07-03T23:53:55.877171Z",
      "ended_at": "2026-07-03T23:53:56.546165Z",
      "stdout": "",
      "stderr": ""
    },
    {
      "script": "gallup.py",
      "returncode": 0,
      "started_at": "2026-07-03T23:53:56.546191Z",
      "ended_at": "2026-07-03T23:53:56.596873Z",
      "stdout": "⚠️  Skipping parsing: gallup.py (site temporarily unavailable)\n✅ Stub RSS written: /home/runner/work/parser_en/parser_en/backend/../gallup.xml\n",
      "stderr": ""
    },
    {
      "script": "gq.py",
      "returncode": 0,
      "started_at": "2026-07-03T23:53:56.596891Z",
      "ended_at": "2026-07-03T23:53:59.260071Z",
      "stdout": "",
      "stderr": ""
    },
    {
      "script": "macleans1.py",
      "returncode": 0,
      "started_at": "2026-07-03T23:53:59.260097Z",
      "ended_at": "2026-07-03T23:53:59.311008Z",
      "stdout": "⚠️  Skipping parsing: macleans1.py (site temporarily unavailable)\n✅ Stub RSS written: /home/runner/work/parser_en/parser_en/backend/../macleans1.xml\n",
      "stderr": ""
    },
    {
      "script": "newyorker.py",
      "returncode": 0,
      "started_at": "2026-07-03T23:53:59.311029Z",
      "ended_at": "2026-07-03T23:53:59.661782Z",
      "stdout": "",
      "stderr": ""
    },
    {
      "script": "nyt.py",
      "returncode": 0,
      "started_at": "2026-07-03T23:53:59.661808Z",
      "ended_at": "2026-07-03T23:54:00.174711Z",
      "stdout": "",
      "stderr": ""
    },
    {
      "script": "nytmag.py",
      "returncode": 0,
      "started_at": "2026-07-03T23:54:00.174736Z",
      "ended_at": "2026-07-03T23:54:01.092965Z",
      "stdout": "",
      "stderr": ""
    },
    {
      "script": "pitchfork.py",
      "returncode": 0,
      "started_at": "2026-07-03T23:54:01.092993Z",
      "ended_at": "2026-07-03T23:54:01.628962Z",
      "stdout": "📰 Found 0 articles. Fetching dates...\n✅ pitchfork.xml generated successfully\n",
      "stderr": ""
    },
    {
      "script": "reuters.py",
      "returncode": 0,
      "started_at": "2026-07-03T23:54:01.628987Z",
      "ended_at": "2026-07-03T23:54:26.397455Z",
      "stdout": "Collected 0 items\n",
      "stderr": ""
    },
    {
      "script": "semafor.py",
      "returncode": 0,
      "started_at": "2026-07-03T23:54:26.397481Z",
      "ended_at": "2026-07-03T23:54:26.842859Z",
      "stdout": "",
      "stderr": ""
    },
    {
      "script": "vulture.py",
      "returncode": 0,
      "started_at": "2026-07-03T23:54:26.842885Z",
      "ended_at": "2026-07-03T23:54:27.216716Z",
      "stdout": "",
      "stderr": ""
    },
    {
      "script": "wired.py",
      "returncode": 0,
      "started_at": "2026-07-03T23:54:27.216741Z",
      "ended_at": "2026-07-03T23:54:27.650685Z",
      "stdout": "",
      "stderr": ""
    },
    {
      "script": "wp_internet.py",
      "returncode": 0,
      "started_at": "2026-07-03T23:54:27.650712Z",
      "ended_at": "2026-07-03T23:54:31.664570Z",
      "stdout": "✅ RSS создан: /home/runner/work/parser_en/parser_en/wapo_internet.xml, статей собрано: 0\n",
      "stderr": ""
    },
    {
      "script": "wp_inv.py",
      "returncode": 0,
      "started_at": "2026-07-03T23:54:31.664593Z",
      "ended_at": "2026-07-03T23:54:35.460610Z",
      "stdout": "RSS создан: /home/runner/work/parser_en/parser_en/wapo_inv.xml\n",
      "stderr": ""
    },
    {
      "script": "wp_tech.py",
      "returncode": 0,
      "started_at": "2026-07-03T23:54:35.460634Z",
      "ended_at": "2026-07-03T23:54:40.261804Z",
      "stdout": "Добавлена статья: Tech in Your Life\nДобавлена статья: Your Data and Privacy\nДобавлена статья: Internet Access\nДобавлена статья: What's New\nДобавлена статья: Ethical Issues\n✅ RSS создан: /home/runner/work/parser_en/parser_en/wapo_tech.xml, статей собрано: 5\n",
      "stderr": ""
    }
  ]
}