{
  "backend_dir": "/home/runner/work/parser_en/parser_en/backend",
  "total": 12,
  "success": 12,
  "failures": 0,
  "results": [
    {
      "script": "atlantic.py",
      "returncode": 0,
      "started_at": "2025-09-03T18:30:21.034361Z",
      "ended_at": "2025-09-03T18:30:21.586695Z",
      "stdout": "",
      "stderr": ""
    },
    {
      "script": "gq.py",
      "returncode": 0,
      "started_at": "2025-09-03T18:30:21.586719Z",
      "ended_at": "2025-09-03T18:30:22.060376Z",
      "stdout": "",
      "stderr": ""
    },
    {
      "script": "newyorker.py",
      "returncode": 0,
      "started_at": "2025-09-03T18:30:22.060400Z",
      "ended_at": "2025-09-03T18:30:22.535273Z",
      "stdout": "",
      "stderr": ""
    },
    {
      "script": "nyt.py",
      "returncode": 0,
      "started_at": "2025-09-03T18:30:22.535296Z",
      "ended_at": "2025-09-03T18:30:22.884243Z",
      "stdout": "",
      "stderr": ""
    },
    {
      "script": "nytmag.py",
      "returncode": 0,
      "started_at": "2025-09-03T18:30:22.884269Z",
      "ended_at": "2025-09-03T18:30:23.159868Z",
      "stdout": "",
      "stderr": ""
    },
    {
      "script": "reuters.py",
      "returncode": 0,
      "started_at": "2025-09-03T18:30:23.159889Z",
      "ended_at": "2025-09-03T18:30:47.736405Z",
      "stdout": "Collected 0 items\n",
      "stderr": ""
    },
    {
      "script": "semafor.py",
      "returncode": 0,
      "started_at": "2025-09-03T18:30:47.736424Z",
      "ended_at": "2025-09-03T18:30:48.103389Z",
      "stdout": "",
      "stderr": ""
    },
    {
      "script": "vulture.py",
      "returncode": 0,
      "started_at": "2025-09-03T18:30:48.103412Z",
      "ended_at": "2025-09-03T18:30:48.542022Z",
      "stdout": "",
      "stderr": ""
    },
    {
      "script": "wired.py",
      "returncode": 0,
      "started_at": "2025-09-03T18:30:48.542044Z",
      "ended_at": "2025-09-03T18:30:52.577845Z",
      "stdout": "",
      "stderr": ""
    },
    {
      "script": "wp_internet.py",
      "returncode": 0,
      "started_at": "2025-09-03T18:30:52.577870Z",
      "ended_at": "2025-09-03T18:30:56.636068Z",
      "stdout": "✅ RSS создан: /home/runner/work/parser_en/parser_en/wapo_internet.xml, статей собрано: 0\n",
      "stderr": ""
    },
    {
      "script": "wp_inv.py",
      "returncode": 0,
      "started_at": "2025-09-03T18:30:56.636088Z",
      "ended_at": "2025-09-03T18:31:00.251381Z",
      "stdout": "RSS создан: /home/runner/work/parser_en/parser_en/wapo_inv.xml\n",
      "stderr": ""
    },
    {
      "script": "wp_tech.py",
      "returncode": 0,
      "started_at": "2025-09-03T18:31:00.251403Z",
      "ended_at": "2025-09-03T18:31:04.900929Z",
      "stdout": "Добавлена статья: Tech in Your Life\nДобавлена статья: Your Data and Privacy\nДобавлена статья: Internet Access\nДобавлена статья: What's New\nДобавлена статья: Ethical Issues\n✅ RSS создан: /home/runner/work/parser_en/parser_en/wapo_tech.xml, статей собрано: 5\n",
      "stderr": ""
    }
  ]
}