{
  "backend_dir": "/home/runner/work/parser_en/parser_en/backend",
  "total": 12,
  "success": 12,
  "failures": 0,
  "results": [
    {
      "script": "atlantic.py",
      "returncode": 0,
      "started_at": "2025-09-26T07:22:15.539025Z",
      "ended_at": "2025-09-26T07:22:16.019090Z",
      "stdout": "",
      "stderr": ""
    },
    {
      "script": "gq.py",
      "returncode": 0,
      "started_at": "2025-09-26T07:22:16.019114Z",
      "ended_at": "2025-09-26T07:22:18.752386Z",
      "stdout": "",
      "stderr": ""
    },
    {
      "script": "newyorker.py",
      "returncode": 0,
      "started_at": "2025-09-26T07:22:18.752406Z",
      "ended_at": "2025-09-26T07:22:20.392629Z",
      "stdout": "",
      "stderr": ""
    },
    {
      "script": "nyt.py",
      "returncode": 0,
      "started_at": "2025-09-26T07:22:20.392651Z",
      "ended_at": "2025-09-26T07:22:20.797386Z",
      "stdout": "",
      "stderr": ""
    },
    {
      "script": "nytmag.py",
      "returncode": 0,
      "started_at": "2025-09-26T07:22:20.797408Z",
      "ended_at": "2025-09-26T07:22:21.189861Z",
      "stdout": "",
      "stderr": ""
    },
    {
      "script": "reuters.py",
      "returncode": 0,
      "started_at": "2025-09-26T07:22:21.189889Z",
      "ended_at": "2025-09-26T07:22:45.773092Z",
      "stdout": "Collected 0 items\n",
      "stderr": ""
    },
    {
      "script": "semafor.py",
      "returncode": 0,
      "started_at": "2025-09-26T07:22:45.773115Z",
      "ended_at": "2025-09-26T07:22:46.264359Z",
      "stdout": "",
      "stderr": ""
    },
    {
      "script": "vulture.py",
      "returncode": 0,
      "started_at": "2025-09-26T07:22:46.264382Z",
      "ended_at": "2025-09-26T07:22:46.513908Z",
      "stdout": "",
      "stderr": ""
    },
    {
      "script": "wired.py",
      "returncode": 0,
      "started_at": "2025-09-26T07:22:46.513935Z",
      "ended_at": "2025-09-26T07:23:00.763797Z",
      "stdout": "[WARN] Не удалось получить дату для https://www.wired.com/visual-story/politics-issue-all-hail-the-technocracy/\n[WARN] Не удалось получить дату для https://www.wired.com/visual-story/politics-issue-doge-oral-history/\n[WARN] Не удалось получить дату для https://www.wired.com/visual-story/politics-issue-2025-political-power-users/\n[WARN] Не удалось получить дату для https://www.wired.com/visual-story/politics-issue-kat-out-of-the-bag/\n[WARN] Не удалось получить дату для https://www.wired.com/visual-story/politics-issue-boom-goes-bust/\n[WARN] Не удалось получить дату для https://www.wired.com/visual-story/politics-issue-space-invaders/\n[WARN] Не удалось получить дату для https://www.wired.com/visual-story/politics-issue-farenheit-5g/\n",
      "stderr": ""
    },
    {
      "script": "wp_internet.py",
      "returncode": 0,
      "started_at": "2025-09-26T07:23:00.763841Z",
      "ended_at": "2025-09-26T07:23:06.114621Z",
      "stdout": "✅ RSS создан: /home/runner/work/parser_en/parser_en/wapo_internet.xml, статей собрано: 0\n",
      "stderr": ""
    },
    {
      "script": "wp_inv.py",
      "returncode": 0,
      "started_at": "2025-09-26T07:23:06.114644Z",
      "ended_at": "2025-09-26T07:23:10.004138Z",
      "stdout": "RSS создан: /home/runner/work/parser_en/parser_en/wapo_inv.xml\n",
      "stderr": ""
    },
    {
      "script": "wp_tech.py",
      "returncode": 0,
      "started_at": "2025-09-26T07:23:10.004161Z",
      "ended_at": "2025-09-26T07:23:13.485702Z",
      "stdout": "Добавлена статья: Tech in Your Life\nДобавлена статья: Your Data and Privacy\nДобавлена статья: Internet Access\nДобавлена статья: What's New\nДобавлена статья: Ethical Issues\n✅ RSS создан: /home/runner/work/parser_en/parser_en/wapo_tech.xml, статей собрано: 5\n",
      "stderr": ""
    }
  ]
}