{
  "backend_dir": "/home/runner/work/parser_en/parser_en/backend",
  "total": 15,
  "success": 15,
  "failures": 0,
  "results": [
    {
      "script": "atlantic.py",
      "returncode": 0,
      "started_at": "2026-04-07T01:13:08.760411Z",
      "ended_at": "2026-04-07T01:13:09.400192Z",
      "stdout": "",
      "stderr": ""
    },
    {
      "script": "gallup.py",
      "returncode": 0,
      "started_at": "2026-04-07T01:13:09.400225Z",
      "ended_at": "2026-04-07T01:13:09.448441Z",
      "stdout": "⚠️  Skipping parsing: gallup.py (site temporarily unavailable)\n✅ Stub RSS written: /home/runner/work/parser_en/parser_en/backend/../gallup.xml\n",
      "stderr": ""
    },
    {
      "script": "gq.py",
      "returncode": 0,
      "started_at": "2026-04-07T01:13:09.448459Z",
      "ended_at": "2026-04-07T01:13:11.268576Z",
      "stdout": "",
      "stderr": ""
    },
    {
      "script": "macleans1.py",
      "returncode": 0,
      "started_at": "2026-04-07T01:13:11.268600Z",
      "ended_at": "2026-04-07T01:13:11.316305Z",
      "stdout": "⚠️  Skipping parsing: macleans1.py (site temporarily unavailable)\n✅ Stub RSS written: /home/runner/work/parser_en/parser_en/backend/../macleans1.xml\n",
      "stderr": ""
    },
    {
      "script": "newyorker.py",
      "returncode": 0,
      "started_at": "2026-04-07T01:13:11.316341Z",
      "ended_at": "2026-04-07T01:13:13.030250Z",
      "stdout": "",
      "stderr": ""
    },
    {
      "script": "nyt.py",
      "returncode": 0,
      "started_at": "2026-04-07T01:13:13.030310Z",
      "ended_at": "2026-04-07T01:13:13.825136Z",
      "stdout": "",
      "stderr": ""
    },
    {
      "script": "nytmag.py",
      "returncode": 0,
      "started_at": "2026-04-07T01:13:13.825159Z",
      "ended_at": "2026-04-07T01:13:14.287759Z",
      "stdout": "",
      "stderr": ""
    },
    {
      "script": "pitchfork.py",
      "returncode": 0,
      "started_at": "2026-04-07T01:13:14.287783Z",
      "ended_at": "2026-04-07T01:13:20.107035Z",
      "stdout": "📰 Found 0 articles. Fetching dates...\n✅ pitchfork.xml generated successfully\n",
      "stderr": ""
    },
    {
      "script": "reuters.py",
      "returncode": 0,
      "started_at": "2026-04-07T01:13:20.107059Z",
      "ended_at": "2026-04-07T01:13:45.000912Z",
      "stdout": "Collected 0 items\n",
      "stderr": ""
    },
    {
      "script": "semafor.py",
      "returncode": 0,
      "started_at": "2026-04-07T01:13:45.000936Z",
      "ended_at": "2026-04-07T01:13:45.357474Z",
      "stdout": "",
      "stderr": ""
    },
    {
      "script": "vulture.py",
      "returncode": 0,
      "started_at": "2026-04-07T01:13:45.357497Z",
      "ended_at": "2026-04-07T01:13:45.658509Z",
      "stdout": "",
      "stderr": ""
    },
    {
      "script": "wired.py",
      "returncode": 0,
      "started_at": "2026-04-07T01:13:45.658529Z",
      "ended_at": "2026-04-07T01:13:46.196994Z",
      "stdout": "",
      "stderr": ""
    },
    {
      "script": "wp_internet.py",
      "returncode": 0,
      "started_at": "2026-04-07T01:13:46.197019Z",
      "ended_at": "2026-04-07T01:13:49.930740Z",
      "stdout": "✅ RSS создан: /home/runner/work/parser_en/parser_en/wapo_internet.xml, статей собрано: 0\n",
      "stderr": ""
    },
    {
      "script": "wp_inv.py",
      "returncode": 0,
      "started_at": "2026-04-07T01:13:49.930763Z",
      "ended_at": "2026-04-07T01:13:53.701925Z",
      "stdout": "RSS создан: /home/runner/work/parser_en/parser_en/wapo_inv.xml\n",
      "stderr": ""
    },
    {
      "script": "wp_tech.py",
      "returncode": 0,
      "started_at": "2026-04-07T01:13:53.701948Z",
      "ended_at": "2026-04-07T01:13:57.574549Z",
      "stdout": "Добавлена статья: Tech in Your Life\nДобавлена статья: Your Data and Privacy\nДобавлена статья: Internet Access\nДобавлена статья: What's New\nДобавлена статья: Ethical Issues\n✅ RSS создан: /home/runner/work/parser_en/parser_en/wapo_tech.xml, статей собрано: 5\n",
      "stderr": ""
    }
  ]
}