{
  "backend_dir": "/home/runner/work/parser_en/parser_en/backend",
  "total": 12,
  "success": 12,
  "failures": 0,
  "results": [
    {
      "script": "atlantic.py",
      "returncode": 0,
      "started_at": "2025-09-13T23:17:36.501819Z",
      "ended_at": "2025-09-13T23:17:36.955021Z",
      "stdout": "",
      "stderr": ""
    },
    {
      "script": "gq.py",
      "returncode": 0,
      "started_at": "2025-09-13T23:17:36.955044Z",
      "ended_at": "2025-09-13T23:17:44.167423Z",
      "stdout": "",
      "stderr": ""
    },
    {
      "script": "newyorker.py",
      "returncode": 0,
      "started_at": "2025-09-13T23:17:44.167446Z",
      "ended_at": "2025-09-13T23:17:44.668318Z",
      "stdout": "",
      "stderr": ""
    },
    {
      "script": "nyt.py",
      "returncode": 0,
      "started_at": "2025-09-13T23:17:44.668341Z",
      "ended_at": "2025-09-13T23:17:45.175822Z",
      "stdout": "",
      "stderr": ""
    },
    {
      "script": "nytmag.py",
      "returncode": 0,
      "started_at": "2025-09-13T23:17:45.175843Z",
      "ended_at": "2025-09-13T23:17:45.535565Z",
      "stdout": "",
      "stderr": ""
    },
    {
      "script": "reuters.py",
      "returncode": 0,
      "started_at": "2025-09-13T23:17:45.535588Z",
      "ended_at": "2025-09-13T23:18:10.390794Z",
      "stdout": "Collected 0 items\n",
      "stderr": ""
    },
    {
      "script": "semafor.py",
      "returncode": 0,
      "started_at": "2025-09-13T23:18:10.390819Z",
      "ended_at": "2025-09-13T23:18:10.742614Z",
      "stdout": "",
      "stderr": ""
    },
    {
      "script": "vulture.py",
      "returncode": 0,
      "started_at": "2025-09-13T23:18:10.742635Z",
      "ended_at": "2025-09-13T23:18:11.072408Z",
      "stdout": "",
      "stderr": ""
    },
    {
      "script": "wired.py",
      "returncode": 0,
      "started_at": "2025-09-13T23:18:11.072431Z",
      "ended_at": "2025-09-13T23:18:15.721216Z",
      "stdout": "",
      "stderr": ""
    },
    {
      "script": "wp_internet.py",
      "returncode": 0,
      "started_at": "2025-09-13T23:18:15.721240Z",
      "ended_at": "2025-09-13T23:18:19.767722Z",
      "stdout": "✅ RSS создан: /home/runner/work/parser_en/parser_en/wapo_internet.xml, статей собрано: 0\n",
      "stderr": ""
    },
    {
      "script": "wp_inv.py",
      "returncode": 0,
      "started_at": "2025-09-13T23:18:19.767744Z",
      "ended_at": "2025-09-13T23:18:23.285991Z",
      "stdout": "RSS создан: /home/runner/work/parser_en/parser_en/wapo_inv.xml\n",
      "stderr": ""
    },
    {
      "script": "wp_tech.py",
      "returncode": 0,
      "started_at": "2025-09-13T23:18:23.286016Z",
      "ended_at": "2025-09-13T23:18:26.875269Z",
      "stdout": "Добавлена статья: Tech in Your Life\nДобавлена статья: Your Data and Privacy\nДобавлена статья: Internet Access\nДобавлена статья: What's New\nДобавлена статья: Ethical Issues\n✅ RSS создан: /home/runner/work/parser_en/parser_en/wapo_tech.xml, статей собрано: 5\n",
      "stderr": ""
    }
  ]
}